uglysoup/__init__.py
uglysoup/uglysoup.py
uglysoup-1.3.dist-info/METADATA
uglysoup-1.3.dist-info/WHEEL
uglysoup-1.3.dist-info/entry_points.txt
uglysoup-1.3.dist-info/top_level.txt
uglysoup-1.3.dist-info/RECORD
